inverse/__init__.py
inverse/__version__.py
inverse/c_ext/a2vector_ops.c
inverse/ctypes_loc/__init__.py
inverse/ctypes_loc/b__/clib
inverse/ctypes_loc/b__/clib.c
inverse/ctypes_loc/b__/clibrary.so
inverse/ctypes_loc/b__/clibSHARED.so
inverse/ctypes_loc/b__/ctypes_class_float.py
inverse/ctypes_loc/b__/deneme_sum.py
inverse/ctypes_loc/b__/deneme_vector.py
inverse/ctypes_loc/b__/lu_comp.c
inverse/ctypes_loc/b__/sum.c
inverse/ctypes_loc/ctypes_class.py
inverse/ctypes_loc/get_c_loc.py
inverse/ctypes_loc/vector_ops.c
inverse/ctypes_loc/vector_ops.so
inverse/ctypes_loc/vector_opsMAC
inverse/ctypes_loc/vector_opsSHARED.so
inverse/src/__init__.py
inverse/src/benchmarks/__init__.py
inverse/src/benchmarks/alternatives.py
inverse/src/benchmarks/vector_nonvector.py
inverse/src/benchmarks/vector_ops_timeit.py
inverse/src/classes/__init__.py
inverse/src/classes/abstract_data.py
inverse/src/classes/abstract_data2.py
inverse/src/classes/buffer_ops.py
inverse/src/classes/buffer_ops_old_yedek.py
inverse/src/classes/db_ops.py
inverse/src/classes/random_sparse.py
inverse/src/classes/randomMatrix.py
inverse/src/classes/sp_matrix.py
inverse/src/engine/__init__.py
inverse/src/engine/algos/__init__.py
inverse/src/engine/algos/_mappings.py
inverse/src/engine/algos/_spsparse.py
inverse/src/engine/algos/_vector_ops.py
inverse/src/engine/algos/base_algo.py
inverse/src/engine/algos/benchmarks/__init__.py
inverse/src/engine/algos/benchmarks/_progress_yedek_0705.py
inverse/src/engine/algos/benchmarks/vector_ops_bench.py
inverse/src/engine/algos/yedek/base_algo_yedek.py
inverse/src/engine/algos_save/_save_base.py
inverse/src/engine/algos_save/_save_sparse.py
inverse/src/engine/base_classes/__init__.py
inverse/src/engine/base_classes/big_matrix_base.py
inverse/src/engine/main.py
inverse/src/engine/main_funcs_to_load.py
inverse/src/engine/matrix_converters.py
inverse/src/engine/nontest_test.py
inverse/src/engine/sp_matrix_ops.py
inverse/src/large_data/__init__.py
inverse-0.0.13.dist-info/LICENSE
inverse-0.0.13.dist-info/METADATA
inverse-0.0.13.dist-info/WHEEL
inverse-0.0.13.dist-info/RECORD
